aigenmol/__init__.py
aigenmol-0.0.0.1.dist-info/entry_points.txt
aigenmol-0.0.0.1.dist-info/WHEEL
aigenmol-0.0.0.1.dist-info/METADATA
aigenmol-0.0.0.1.dist-info/RECORD
