Metadata-Version: 2.1
Name: aigenmol
Version: 0.0.0.1
Summary: AIGenMol
Home-page: https://github.com/takshan/posgen
License: MIT
Author: Rahul Brahma
Author-email: mrbrahma.rahul@gmail.com
Classifier: Development Status :: 5 - Production/Stable
Classifier: License :: OSI Approved :: MIT License
Classifier: Programming Language :: Python :: 2
Classifier: Programming Language :: Python :: 2.7
Classifier: Programming Language :: Python :: 3
Classifier: Programming Language :: Python :: 3.10
Classifier: Programming Language :: Python :: 3.4
Classifier: Programming Language :: Python :: 3.5
Classifier: Programming Language :: Python :: 3.6
Classifier: Programming Language :: Python :: 3.7
Classifier: Programming Language :: Python :: 3.8
Classifier: Programming Language :: Python :: 3.9
Project-URL: Documentation, https://posgen.readthedocs.io
Project-URL: Repository, https://github.com/takshan/posgen
